{
    "openapi": "3.0.0",
    "info": {
        "title": "API de cadastro e pesquisa de usu치rio",
        "description": "API tem como objetivo cadastrar usu치rio na base de dados e buscar com base no cpf",
        "version": "1.0.0"
    },
    "contact": {
        "email": "_ryan.00@academico.ufs.br"
    },
    "paths": {
        "/users/register": {
            "post": {
                "summary": "Cadastro de usuarios",
                "description": "Rota respons치vel por cadastrar usuarios"
                }
            },
        "/users/search": {
            "get": {
                "summary": "Resgatar dados de usuario",
                "description": "Rota respons치vel por resgatar dados de usuario pelo cpf"
                }
            }
        }
}
